PyAR488/HP3325A.py
PyAR488/HP3478A.py
PyAR488/HP436A.py
PyAR488/HP8660D.py
PyAR488/HP8903A.py
PyAR488/PyAR488.py
PyAR488/__init__.py
PyAR488-2.0.15.dist-info/LICENSE
PyAR488-2.0.15.dist-info/METADATA
PyAR488-2.0.15.dist-info/WHEEL
PyAR488-2.0.15.dist-info/top_level.txt
PyAR488-2.0.15.dist-info/RECORD
