Metadata-Version: 2.1
Name: PyAR488
Version: 2.0.15
Summary: module to interface AR488 boards and wide instrument library
Home-page: https://github.com/Minu-IU3IRR/PyAR488
Author: Manuel Minutello
License: MIT
Platform: UNKNOWN
License-File: LICENSE
Requires-Dist: pyserial
Requires-Dist: numpy
Requires-Dist: matplotlib
